upyog/VERSION
upyog/__attr__.py
upyog/__init__.py
upyog/__main__.py
upyog/_compat.py
upyog/cache.py
upyog/config.py
upyog/const.py
upyog/db.py
upyog/exception.py
upyog/limits.py
upyog/log.py
upyog/parallel.py
upyog/psy.py
upyog/table.py
upyog/tree.py
upyog/api/__init__.py
upyog/api/base.py
upyog/api/github.py
upyog/cli/__init__.py
upyog/cli/formatter.py
upyog/cli/parser.py
upyog/cli/util.py
upyog/commands/__init__.py
upyog/commands/util/__init__.py
upyog/data/bootstrap.sql
upyog/data/templates/.keep
upyog/i18n/__init__.py
upyog/i18n/es.json
upyog/i18n/util.py
upyog/jobs/__init__.py
upyog/model/__init__.py
upyog/model/base.py
upyog/model/package.py
upyog/request/__init__.py
upyog/request/response.py
upyog/util/__init__.py
upyog/util/_async.py
upyog/util/_aws.py
upyog/util/_csv.py
upyog/util/_dict.py
upyog/util/_json.py
upyog/util/_math.py
upyog/util/array.py
upyog/util/cli.py
upyog/util/datetime.py
upyog/util/doc.py
upyog/util/environ.py
upyog/util/error.py
upyog/util/fn.py
upyog/util/git.py
upyog/util/imports.py
upyog/util/jobs.py
upyog/util/misc.py
upyog/util/mixin.py
upyog/util/ml.py
upyog/util/op.py
upyog/util/progress.py
upyog/util/proxy.py
upyog/util/query.py
upyog/util/request.py
upyog/util/string.py
upyog/util/system.py
upyog/util/template.py
upyog/util/test.py
upyog/util/types.py
PyUpyog-0.5.15.dist-info/AUTHORS.md
PyUpyog-0.5.15.dist-info/LICENSE
PyUpyog-0.5.15.dist-info/METADATA
PyUpyog-0.5.15.dist-info/WHEEL
PyUpyog-0.5.15.dist-info/entry_points.txt
PyUpyog-0.5.15.dist-info/top_level.txt
PyUpyog-0.5.15.dist-info/RECORD
